prometheusrock/__init__.py
prometheusrock/add_custom_metric.py
prometheusrock/middleware.py
prometheusrock/route.py
prometheusrock/singleton.py
prometheusrock-0.2.0.dist-info/LICENSE
prometheusrock-0.2.0.dist-info/METADATA
prometheusrock-0.2.0.dist-info/WHEEL
prometheusrock-0.2.0.dist-info/top_level.txt
prometheusrock-0.2.0.dist-info/RECORD
