Metadata-Version: 2.1
Name: prometheusrock
Version: 0.2.0
Summary: Prometheus middleware for Starlette and FastAPI
Home-page: https://github.com/kozhushman/prometheusrock
Author: Nikita Kozhushko (kozhushman)
Author-email: kozhushman@gmail.com
License: MIT License
Platform: UNKNOWN
Requires-Dist: starlette
Requires-Dist: prometheus-client
